Planes2D/Planes2D.py
Planes2D/__init__.py
Planes2D-1.2.dist-info/METADATA
Planes2D-1.2.dist-info/WHEEL
Planes2D-1.2.dist-info/top_level.txt
Planes2D-1.2.dist-info/RECORD
