Metadata-Version: 2.1
Name: Planes2D
Version: 1.2
Summary: A simple liblary for creating and managing 2D planes
Author: Komornik
